[{"hjd": "2457277.88501", "camera": "bg", "mag": "12.922", "mag_err": "0.02", "flux": "26.016", "flux_err": "0.479"}, {"hjd": "2457110.57517", "camera": "be", "mag": "12.92", "mag_err": "0.02", "flux": "25.474", "flux_err": "0.469"}, {"hjd": "2457085.62196", "camera": "be", "mag": "12.923", "mag_err": "0.02", "flux": "25.391", "flux_err": "0.467"}, {"hjd": "2457808.68138", "camera": "bg", "mag": "12.908", "mag_err": "0.02", "flux": "26.353", "flux_err": "0.485"}, {"hjd": "2457077.59193", "camera": "be", "mag": "12.962", "mag_err": "0.02", "flux": "24.492", "flux_err": "0.451"}, {"hjd": "2458009.8188", "camera": "bg", "mag": "12.984", "mag_err": "0.02", "flux": "24.57", "flux_err": "0.452"}, {"hjd": "2457971.90763", "camera": "bg", "mag": "12.97", "mag_err": "0.02", "flux": "24.886", "flux_err": "0.458"}, {"hjd": "2458074.80249", "camera": "bg", "mag": "12.961", "mag_err": "0.02", "flux": "25.082", "flux_err": "0.462"}, {"hjd": "2457444.67591", "camera": "bg", "mag": "12.926", "mag_err": "0.02", "flux": "25.904", "flux_err": "0.477"}, {"hjd": "2457268.83679", "camera": "be", "mag": "12.963", "mag_err": "0.02", "flux": "24.485", "flux_err": "0.451"}, {"hjd": "2458134.81591", "camera": "ba", "mag": "12.964", "mag_err": "0.02", "flux": "24.784", "flux_err": "0.456"}, {"hjd": "2458021.86593", "camera": "bg", "mag": "12.917", "mag_err": "0.02", "flux": "26.123", "flux_err": "0.481"}, {"hjd": "2456933.80646", "camera": "be", "mag": "12.959", "mag_err": "0.02", "flux": "24.555", "flux_err": "0.452"}, {"hjd": "2457883.45", "camera": "bg", "mag": "12.891", "mag_err": "0.02", "flux": "26.767", "flux_err": "0.493"}, {"hjd": "2457953.94396", "camera": "bg", "mag": "12.957", "mag_err": "0.02", "flux": "25.184", "flux_err": "0.463"}, {"hjd": "2457468.55939", "camera": "bg", "mag": "12.898", "mag_err": "0.02", "flux": "26.592", "flux_err": "0.489"}, {"hjd": "2456594.11014", "camera": "ba", "mag": "12.9", "mag_err": "0.02", "flux": "26.281", "flux_err": "0.484"}, {"hjd": "2457437.69603", "camera": "bg", "mag": "12.951", "mag_err": "0.02", "flux": "25.329", "flux_err": "0.466"}, {"hjd": "2457741.70594", "camera": "bg", "mag": "12.973", "mag_err": "0.02", "flux": "24.809", "flux_err": "0.456"}, {"hjd": "2456993.69782", "camera": "be", "mag": "12.938", "mag_err": "0.02", "flux": "25.052", "flux_err": "0.461"}, {"hjd": "2458129.61607", "camera": "bg", "mag": "12.952", "mag_err": "0.02", "flux": "25.288", "flux_err": "0.465"}, {"hjd": "2456936.09846", "camera": "ba", "mag": "12.936", "mag_err": "0.02", "flux": "25.419", "flux_err": "0.468"}, {"hjd": "2458022.86835", "camera": "bg", "mag": "12.919", "mag_err": "0.02", "flux": "26.07", "flux_err": "0.48"}, {"hjd": "2457829.58348", "camera": "bg", "mag": "12.919", "mag_err": "0.02", "flux": "26.087", "flux_err": "0.48"}, {"hjd": "2457856.5464", "camera": "bg", "mag": "12.914", "mag_err": "0.02", "flux": "26.195", "flux_err": "0.482"}, {"hjd": "2457589.94115", "camera": "bg", "mag": "13.01", "mag_err": "0.02353", "flux": "23.991", "flux_err": "0.519"}, {"hjd": "2457423.56619", "camera": "bg", "mag": "12.943", "mag_err": "0.02", "flux": "25.509", "flux_err": "0.469"}, {"hjd": "2457807.64879", "camera": "bg", "mag": "12.958", "mag_err": "0.02", "flux": "25.153", "flux_err": "0.463"}, {"hjd": "2456927.81839", "camera": "be", "mag": "12.936", "mag_err": "0.02", "flux": "25.096", "flux_err": "0.462"}, {"hjd": "2457700.65659", "camera": "bg", "mag": "12.894", "mag_err": "0.02", "flux": "26.689", "flux_err": "0.491"}, {"hjd": "2458079.63076", "camera": "bg", "mag": "12.927", "mag_err": "0.02", "flux": "25.899", "flux_err": "0.477"}, {"hjd": "2457982.88567", "camera": "bg", "mag": "12.972", "mag_err": "0.02", "flux": "24.83", "flux_err": "0.457"}, {"hjd": "2457385.72654", "camera": "bg", "mag": "12.941", "mag_err": "0.02", "flux": "25.554", "flux_err": "0.47"}, {"hjd": "2458125.71292", "camera": "bg", "mag": "13.055", "mag_err": "0.02319", "flux": "23.011", "flux_err": "0.491"}, {"hjd": "2457429.71775", "camera": "bg", "mag": "12.964", "mag_err": "0.02", "flux": "25.028", "flux_err": "0.461"}, {"hjd": "2457969.91932", "camera": "bg", "mag": "12.969", "mag_err": "0.02", "flux": "24.913", "flux_err": "0.458"}, {"hjd": "2457621.8684", "camera": "bg", "mag": "12.994", "mag_err": "0.02", "flux": "24.347", "flux_err": "0.448"}, {"hjd": "2457960.92346", "camera": "bg", "mag": "12.91", "mag_err": "0.02", "flux": "26.293", "flux_err": "0.484"}, {"hjd": "2457775.67478", "camera": "bg", "mag": "12.939", "mag_err": "0.02", "flux": "25.611", "flux_err": "0.471"}, {"hjd": "2457372.6222", "camera": "bg", "mag": "13.042", "mag_err": "0.02328", "flux": "23.294", "flux_err": "0.499"}, {"hjd": "2458032.85922", "camera": "bg", "mag": "12.955", "mag_err": "0.02", "flux": "25.234", "flux_err": "0.464"}, {"hjd": "2458152.81936", "camera": "ba", "mag": "12.946", "mag_err": "0.02", "flux": "25.175", "flux_err": "0.463"}, {"hjd": "2457833.60114", "camera": "bg", "mag": "12.963", "mag_err": "0.02", "flux": "25.036", "flux_err": "0.461"}, {"hjd": "2457384.82548", "camera": "bg", "mag": "12.998", "mag_err": "0.02", "flux": "24.239", "flux_err": "0.446"}, {"hjd": "2456991.68338", "camera": "be", "mag": "12.99", "mag_err": "0.02349", "flux": "23.875", "flux_err": "0.516"}, {"hjd": "2457424.70529", "camera": "bg", "mag": "12.887", "mag_err": "0.02", "flux": "26.854", "flux_err": "0.494"}, {"hjd": "2457426.7276", "camera": "bg", "mag": "12.984", "mag_err": "0.02", "flux": "24.557", "flux_err": "0.452"}, {"hjd": "2457396.54621", "camera": "bg", "mag": "12.97", "mag_err": "0.02", "flux": "24.88", "flux_err": "0.458"}, {"hjd": "2457375.55104", "camera": "bg", "mag": "12.973", "mag_err": "0.02", "flux": "24.805", "flux_err": "0.456"}, {"hjd": "2456977.86858", "camera": "be", "mag": "12.919", "mag_err": "0.02", "flux": "25.479", "flux_err": "0.469"}, {"hjd": "2457616.8964", "camera": "bg", "mag": "12.979", "mag_err": "0.02", "flux": "24.674", "flux_err": "0.454"}, {"hjd": "2456950.88533", "camera": "be", "mag": "12.904", "mag_err": "0.02", "flux": "25.838", "flux_err": "0.475"}, {"hjd": "2457287.89946", "camera": "bg", "mag": "12.939", "mag_err": "0.02", "flux": "25.609", "flux_err": "0.471"}, {"hjd": "2456629.87107", "camera": "ba", "mag": "12.936", "mag_err": "0.02", "flux": "25.445", "flux_err": "0.468"}, {"hjd": "2456734.75064", "camera": "ba", "mag": "12.95", "mag_err": "0.02", "flux": "25.113", "flux_err": "0.462"}, {"hjd": "2458004.82243", "camera": "bg", "mag": "13.01", "mag_err": "0.02353", "flux": "23.985", "flux_err": "0.519"}, {"hjd": "2457440.68316", "camera": "bg", "mag": "12.901", "mag_err": "0.02", "flux": "26.518", "flux_err": "0.488"}, {"hjd": "2457840.58865", "camera": "bg", "mag": "12.916", "mag_err": "0.02", "flux": "26.162", "flux_err": "0.481"}, {"hjd": "2457787.59796", "camera": "bg", "mag": "12.961", "mag_err": "0.02", "flux": "25.102", "flux_err": "0.462"}, {"hjd": "2457006.73283", "camera": "be", "mag": "13.007", "mag_err": "0.02336", "flux": "23.504", "flux_err": "0.505"}, {"hjd": "2457340.81463", "camera": "bg", "mag": "12.978", "mag_err": "0.02", "flux": "24.695", "flux_err": "0.454"}, {"hjd": "2457850.55904", "camera": "bg", "mag": "12.961", "mag_err": "0.02", "flux": "25.1", "flux_err": "0.462"}, {"hjd": "2457415.72208", "camera": "bg", "mag": "12.955", "mag_err": "0.02", "flux": "25.221", "flux_err": "0.464"}, {"hjd": "2457739.66023", "camera": "bg", "mag": "12.866", "mag_err": "0.02", "flux": "27.384", "flux_err": "0.504"}, {"hjd": "2456998.93711", "camera": "ba", "mag": "12.982", "mag_err": "0.02", "flux": "24.372", "flux_err": "0.448"}, {"hjd": "2457999.84042", "camera": "bg", "mag": "12.917", "mag_err": "0.02", "flux": "26.118", "flux_err": "0.481"}, {"hjd": "2457979.88842", "camera": "bg", "mag": "12.938", "mag_err": "0.02", "flux": "25.636", "flux_err": "0.472"}, {"hjd": "2457475.58773", "camera": "bg", "mag": "12.919", "mag_err": "0.02", "flux": "26.074", "flux_err": "0.48"}, {"hjd": "2457256.89455", "camera": "be", "mag": "12.921", "mag_err": "0.02", "flux": "25.44", "flux_err": "0.468"}, {"hjd": "2457097.60697", "camera": "be", "mag": "12.938", "mag_err": "0.02", "flux": "25.038", "flux_err": "0.461"}, {"hjd": "2456932.80995", "camera": "be", "mag": "12.975", "mag_err": "0.02361", "flux": "24.214", "flux_err": "0.526"}, {"hjd": "2458452.00497", "camera": "ba", "mag": "12.968", "mag_err": "0.02", "flux": "24.667", "flux_err": "0.454"}, {"hjd": "2458127.62746", "camera": "bg", "mag": "12.913", "mag_err": "0.02", "flux": "26.236", "flux_err": "0.483"}, {"hjd": "2457701.79339", "camera": "bg", "mag": "12.938", "mag_err": "0.02", "flux": "25.634", "flux_err": "0.472"}, {"hjd": "2457438.72555", "camera": "ba", "mag": "12.904", "mag_err": "0.02", "flux": "26.171", "flux_err": "0.482"}, {"hjd": "2457702.64953", "camera": "bg", "mag": "12.958", "mag_err": "0.02", "flux": "25.17", "flux_err": "0.463"}, {"hjd": "2457846.57217", "camera": "bg", "mag": "12.98", "mag_err": "0.02", "flux": "24.665", "flux_err": "0.454"}, {"hjd": "2457039.64717", "camera": "be", "mag": "12.952", "mag_err": "0.02", "flux": "24.734", "flux_err": "0.455"}, {"hjd": "2458012.80416", "camera": "bg", "mag": "12.988", "mag_err": "0.02", "flux": "24.473", "flux_err": "0.45"}, {"hjd": "2456993.94248", "camera": "ba", "mag": "12.918", "mag_err": "0.02", "flux": "25.866", "flux_err": "0.476"}, {"hjd": "2457789.75332", "camera": "ba", "mag": "12.9", "mag_err": "0.02", "flux": "26.265", "flux_err": "0.483"}, {"hjd": "2458152.68076", "camera": "bg", "mag": "11.598", "mag_err": "0.02", "flux": "88.025", "flux_err": "1.62"}, {"hjd": "2457419.74745", "camera": "bg", "mag": "12.976", "mag_err": "0.02", "flux": "24.749", "flux_err": "0.455"}, {"hjd": "2458085.62858", "camera": "bg", "mag": "12.946", "mag_err": "0.02", "flux": "25.439", "flux_err": "0.468"}, {"hjd": "2457715.72023", "camera": "bg", "mag": "12.915", "mag_err": "0.02", "flux": "26.172", "flux_err": "0.482"}, {"hjd": "2457336.72839", "camera": "bg", "mag": "12.968", "mag_err": "0.02", "flux": "24.92", "flux_err": "0.459"}, {"hjd": "2457399.76861", "camera": "bg", "mag": "12.96", "mag_err": "0.02", "flux": "25.124", "flux_err": "0.462"}, {"hjd": "2457318.79724", "camera": "bg", "mag": "12.98", "mag_err": "0.02", "flux": "24.664", "flux_err": "0.454"}, {"hjd": "2457324.0386", "camera": "ba", "mag": "12.928", "mag_err": "0.02", "flux": "25.612", "flux_err": "0.471"}, {"hjd": "2457746.62391", "camera": "bg", "mag": "12.924", "mag_err": "0.02", "flux": "25.968", "flux_err": "0.478"}, {"hjd": "2458124.89914", "camera": "ba", "mag": "12.952", "mag_err": "0.02", "flux": "25.034", "flux_err": "0.461"}, {"hjd": "2457866.5026", "camera": "bg", "mag": "12.99", "mag_err": "0.02", "flux": "24.426", "flux_err": "0.449"}, {"hjd": "2456984.71745", "camera": "be", "mag": "12.961", "mag_err": "0.02", "flux": "24.511", "flux_err": "0.451"}, {"hjd": "2457434.70229", "camera": "bg", "mag": "12.98", "mag_err": "0.02", "flux": "24.665", "flux_err": "0.454"}, {"hjd": "2458433.04413", "camera": "ba", "mag": "12.98", "mag_err": "0.02", "flux": "24.427", "flux_err": "0.449"}, {"hjd": "2457072.62259", "camera": "be", "mag": "12.973", "mag_err": "0.02", "flux": "24.261", "flux_err": "0.446"}, {"hjd": "2457407.68363", "camera": "bg", "mag": "12.958", "mag_err": "0.02", "flux": "25.152", "flux_err": "0.463"}, {"hjd": "2457431.70458", "camera": "bg", "mag": "12.949", "mag_err": "0.02", "flux": "25.378", "flux_err": "0.467"}, {"hjd": "2457709.85298", "camera": "bg", "mag": "12.971", "mag_err": "0.02", "flux": "24.864", "flux_err": "0.458"}, {"hjd": "2457694.68619", "camera": "bg", "mag": "12.966", "mag_err": "0.02", "flux": "24.968", "flux_err": "0.459"}, {"hjd": "2457265.84634", "camera": "be", "mag": "12.959", "mag_err": "0.02", "flux": "24.57", "flux_err": "0.452"}, {"hjd": "2457019.67608", "camera": "be", "mag": "12.963", "mag_err": "0.02", "flux": "24.47", "flux_err": "0.45"}, {"hjd": "2457018.9234", "camera": "ba", "mag": "12.968", "mag_err": "0.02", "flux": "24.683", "flux_err": "0.454"}, {"hjd": "2457796.64136", "camera": "bg", "mag": "12.955", "mag_err": "0.02", "flux": "25.228", "flux_err": "0.464"}, {"hjd": "2458173.56521", "camera": "bg", "mag": "12.951", "mag_err": "0.02", "flux": "25.331", "flux_err": "0.466"}, {"hjd": "2457994.8528", "camera": "bg", "mag": "13.037", "mag_err": "0.02332", "flux": "23.389", "flux_err": "0.502"}, {"hjd": "2457370.7446", "camera": "bg", "mag": "12.903", "mag_err": "0.02", "flux": "26.472", "flux_err": "0.487"}, {"hjd": "2457670.82696", "camera": "bg", "mag": "12.951", "mag_err": "0.02", "flux": "25.333", "flux_err": "0.466"}, {"hjd": "2457830.52257", "camera": "bg", "mag": "12.989", "mag_err": "0.02", "flux": "24.444", "flux_err": "0.45"}, {"hjd": "2457001.9494", "camera": "ba", "mag": "12.93", "mag_err": "0.02", "flux": "25.55", "flux_err": "0.47"}, {"hjd": "2458415.05472", "camera": "ba", "mag": "12.976", "mag_err": "0.02", "flux": "24.514", "flux_err": "0.451"}, {"hjd": "2456971.73206", "camera": "be", "mag": "12.977", "mag_err": "0.02359", "flux": "24.161", "flux_err": "0.524"}, {"hjd": "2457805.68019", "camera": "bg", "mag": "12.912", "mag_err": "0.02", "flux": "26.256", "flux_err": "0.483"}, {"hjd": "2456980.75122", "camera": "be", "mag": "12.963", "mag_err": "0.02", "flux": "24.478", "flux_err": "0.45"}, {"hjd": "2457319.83585", "camera": "bg", "mag": "12.917", "mag_err": "0.02", "flux": "26.135", "flux_err": "0.481"}, {"hjd": "2457439.5531", "camera": "bg", "mag": "12.931", "mag_err": "0.02", "flux": "25.8", "flux_err": "0.475"}, {"hjd": "2457129.51813", "camera": "be", "mag": "12.905", "mag_err": "0.02", "flux": "25.823", "flux_err": "0.475"}, {"hjd": "2457684.806", "camera": "bg", "mag": "12.911", "mag_err": "0.02", "flux": "26.282", "flux_err": "0.484"}, {"hjd": "2457066.60386", "camera": "be", "mag": "12.918", "mag_err": "0.02", "flux": "25.512", "flux_err": "0.469"}, {"hjd": "2457486.55092", "camera": "bg", "mag": "12.911", "mag_err": "0.02", "flux": "26.278", "flux_err": "0.484"}, {"hjd": "2457252.88147", "camera": "be", "mag": "12.94", "mag_err": "0.02", "flux": "25.006", "flux_err": "0.46"}, {"hjd": "2456992.93355", "camera": "ba", "mag": "12.928", "mag_err": "0.02", "flux": "25.638", "flux_err": "0.472"}, {"hjd": "2457119.51226", "camera": "be", "mag": "12.996", "mag_err": "0.02344", "flux": "23.741", "flux_err": "0.512"}, {"hjd": "2457801.54037", "camera": "bg", "mag": "12.919", "mag_err": "0.02", "flux": "26.085", "flux_err": "0.48"}, {"hjd": "2458146.65633", "camera": "bg", "mag": "12.964", "mag_err": "0.02", "flux": "25.017", "flux_err": "0.46"}, {"hjd": "2457378.53239", "camera": "bg", "mag": "12.906", "mag_err": "0.02", "flux": "26.383", "flux_err": "0.485"}, {"hjd": "2457609.89749", "camera": "bg", "mag": "12.964", "mag_err": "0.02", "flux": "25.011", "flux_err": "0.46"}, {"hjd": "2457061.65279", "camera": "be", "mag": "12.972", "mag_err": "0.02", "flux": "24.263", "flux_err": "0.446"}, {"hjd": "2456966.74153", "camera": "be", "mag": "12.923", "mag_err": "0.02", "flux": "25.399", "flux_err": "0.467"}, {"hjd": "2457836.58053", "camera": "bg", "mag": "12.922", "mag_err": "0.02", "flux": "25.999", "flux_err": "0.478"}, {"hjd": "2457668.76061", "camera": "bg", "mag": "12.939", "mag_err": "0.02", "flux": "25.614", "flux_err": "0.471"}, {"hjd": "2457782.66194", "camera": "bg", "mag": "12.866", "mag_err": "0.02", "flux": "27.391", "flux_err": "0.504"}, {"hjd": "2457273.83001", "camera": "be", "mag": "12.946", "mag_err": "0.02", "flux": "24.869", "flux_err": "0.458"}, {"hjd": "2456886.89138", "camera": "be", "mag": "12.968", "mag_err": "0.02", "flux": "24.363", "flux_err": "0.448"}, {"hjd": "2457376.83722", "camera": "bg", "mag": "12.972", "mag_err": "0.02", "flux": "24.832", "flux_err": "0.457"}, {"hjd": "2457380.82828", "camera": "bg", "mag": "13.011", "mag_err": "0.02352", "flux": "23.956", "flux_err": "0.518"}, {"hjd": "2457441.62196", "camera": "bg", "mag": "12.961", "mag_err": "0.02", "flux": "25.087", "flux_err": "0.462"}, {"hjd": "2456924.82089", "camera": "be", "mag": "12.936", "mag_err": "0.02", "flux": "25.085", "flux_err": "0.462"}, {"hjd": "2457034.76109", "camera": "be", "mag": "12.948", "mag_err": "0.02", "flux": "24.82", "flux_err": "0.457"}, {"hjd": "2458083.61896", "camera": "bg", "mag": "12.976", "mag_err": "0.02", "flux": "24.756", "flux_err": "0.456"}, {"hjd": "2456877.93739", "camera": "be", "mag": "12.962", "mag_err": "0.02", "flux": "24.487", "flux_err": "0.451"}, {"hjd": "2457662.75763", "camera": "bg", "mag": "12.918", "mag_err": "0.02", "flux": "26.094", "flux_err": "0.48"}, {"hjd": "2457422.60826", "camera": "bg", "mag": "12.995", "mag_err": "0.02", "flux": "24.319", "flux_err": "0.447"}, {"hjd": "2457405.69985", "camera": "bg", "mag": "12.9", "mag_err": "0.02", "flux": "26.545", "flux_err": "0.488"}, {"hjd": "2457727.671", "camera": "bg", "mag": "12.912", "mag_err": "0.02", "flux": "26.258", "flux_err": "0.483"}, {"hjd": "2457635.88633", "camera": "bg", "mag": "12.947", "mag_err": "0.02", "flux": "25.413", "flux_err": "0.468"}, {"hjd": "2457774.73256", "camera": "bg", "mag": "12.88", "mag_err": "0.02", "flux": "27.043", "flux_err": "0.498"}, {"hjd": "2457657.80455", "camera": "bg", "mag": "12.907", "mag_err": "0.02", "flux": "26.369", "flux_err": "0.485"}, {"hjd": "2457713.83211", "camera": "bg", "mag": "12.945", "mag_err": "0.02", "flux": "25.459", "flux_err": "0.468"}, {"hjd": "2457767.87892", "camera": "ba", "mag": "12.966", "mag_err": "0.02", "flux": "24.717", "flux_err": "0.455"}, {"hjd": "2457115.52356", "camera": "be", "mag": "12.976", "mag_err": "0.0236", "flux": "24.172", "flux_err": "0.525"}, {"hjd": "2457016.67852", "camera": "be", "mag": "12.924", "mag_err": "0.02", "flux": "25.374", "flux_err": "0.467"}, {"hjd": "2457825.61525", "camera": "bg", "mag": "12.942", "mag_err": "0.02", "flux": "25.523", "flux_err": "0.47"}, {"hjd": "2457754.60958", "camera": "bg", "mag": "12.918", "mag_err": "0.02", "flux": "26.104", "flux_err": "0.48"}, {"hjd": "2457133.48365", "camera": "be", "mag": "12.904", "mag_err": "0.02", "flux": "25.84", "flux_err": "0.475"}, {"hjd": "2457397.66718", "camera": "bg", "mag": "12.712", "mag_err": "0.02", "flux": "31.547", "flux_err": "0.58"}, {"hjd": "2457804.69291", "camera": "bg", "mag": "12.933", "mag_err": "0.02", "flux": "25.748", "flux_err": "0.474"}, {"hjd": "2457353.83955", "camera": "bg", "mag": "12.968", "mag_err": "0.02", "flux": "24.919", "flux_err": "0.459"}, {"hjd": "2457633.83567", "camera": "bg", "mag": "12.955", "mag_err": "0.02", "flux": "25.226", "flux_err": "0.464"}, {"hjd": "2457349.81137", "camera": "bg", "mag": "12.991", "mag_err": "0.02", "flux": "24.409", "flux_err": "0.449"}, {"hjd": "2458195.58411", "camera": "bg", "mag": "12.943", "mag_err": "0.02", "flux": "25.521", "flux_err": "0.47"}, {"hjd": "2458191.60783", "camera": "bg", "mag": "12.925", "mag_err": "0.02", "flux": "25.925", "flux_err": "0.477"}, {"hjd": "2458138.80934", "camera": "ba", "mag": "12.97", "mag_err": "0.02", "flux": "24.655", "flux_err": "0.454"}, {"hjd": "2456876.93411", "camera": "be", "mag": "12.875", "mag_err": "0.02", "flux": "26.545", "flux_err": "0.488"}, {"hjd": "2457037.64394", "camera": "be", "mag": "12.957", "mag_err": "0.02", "flux": "24.603", "flux_err": "0.453"}, {"hjd": "2456948.83484", "camera": "be", "mag": "12.979", "mag_err": "0.02358", "flux": "24.126", "flux_err": "0.523"}, {"hjd": "2458128.88517", "camera": "ba", "mag": "12.97", "mag_err": "0.02", "flux": "24.657", "flux_err": "0.454"}, {"hjd": "2457412.85298", "camera": "ba", "mag": "12.888", "mag_err": "0.02", "flux": "26.587", "flux_err": "0.489"}, {"hjd": "2458039.83232", "camera": "bg", "mag": "12.986", "mag_err": "0.02", "flux": "24.51", "flux_err": "0.451"}, {"hjd": "2457605.91184", "camera": "bg", "mag": "12.946", "mag_err": "0.02", "flux": "25.45", "flux_err": "0.468"}, {"hjd": "2458094.62167", "camera": "bg", "mag": "12.958", "mag_err": "0.02", "flux": "25.171", "flux_err": "0.463"}, {"hjd": "2457730.68461", "camera": "bg", "mag": "12.975", "mag_err": "0.02", "flux": "24.77", "flux_err": "0.456"}, {"hjd": "2457649.80886", "camera": "bg", "mag": "12.885", "mag_err": "0.02", "flux": "26.92", "flux_err": "0.495"}, {"hjd": "2456986.97094", "camera": "ba", "mag": "12.966", "mag_err": "0.02", "flux": "24.741", "flux_err": "0.455"}, {"hjd": "2457762.54288", "camera": "bg", "mag": "12.882", "mag_err": "0.02", "flux": "26.972", "flux_err": "0.496"}, {"hjd": "2457479.57646", "camera": "bg", "mag": "12.889", "mag_err": "0.02", "flux": "26.802", "flux_err": "0.493"}, {"hjd": "2458115.9024", "camera": "ba", "mag": "12.934", "mag_err": "0.02", "flux": "25.494", "flux_err": "0.469"}, {"hjd": "2457087.61056", "camera": "be", "mag": "12.914", "mag_err": "0.02", "flux": "25.597", "flux_err": "0.471"}, {"hjd": "2457832.56437", "camera": "bg", "mag": "12.935", "mag_err": "0.02", "flux": "25.7", "flux_err": "0.473"}, {"hjd": "2458040.82892", "camera": "bg", "mag": "12.97", "mag_err": "0.02", "flux": "24.888", "flux_err": "0.458"}, {"hjd": "2457791.67844", "camera": "bg", "mag": "13.013", "mag_err": "0.0235", "flux": "23.908", "flux_err": "0.517"}, {"hjd": "2457831.52575", "camera": "bg", "mag": "12.952", "mag_err": "0.02", "flux": "25.311", "flux_err": "0.466"}, {"hjd": "2457404.73784", "camera": "bg", "mag": "12.92", "mag_err": "0.02", "flux": "26.052", "flux_err": "0.479"}, {"hjd": "2457447.61662", "camera": "bg", "mag": "12.922", "mag_err": "0.02", "flux": "25.997", "flux_err": "0.478"}, {"hjd": "2457124.53714", "camera": "be", "mag": "12.925", "mag_err": "0.02", "flux": "25.35", "flux_err": "0.466"}, {"hjd": "2457116.55992", "camera": "be", "mag": "12.996", "mag_err": "0.02344", "flux": "23.747", "flux_err": "0.512"}, {"hjd": "2457852.54087", "camera": "bg", "mag": "12.872", "mag_err": "0.02", "flux": "27.23", "flux_err": "0.501"}, {"hjd": "2457117.55694", "camera": "be", "mag": "12.907", "mag_err": "0.02", "flux": "25.781", "flux_err": "0.474"}, {"hjd": "2457304.75754", "camera": "bg", "mag": "12.979", "mag_err": "0.02", "flux": "24.672", "flux_err": "0.454"}, {"hjd": "2457821.64199", "camera": "bg", "mag": "12.909", "mag_err": "0.02", "flux": "26.333", "flux_err": "0.485"}, {"hjd": "2457768.58909", "camera": "bg", "mag": "12.965", "mag_err": "0.02", "flux": "24.995", "flux_err": "0.46"}, {"hjd": "2458014.80104", "camera": "bg", "mag": "12.972", "mag_err": "0.02", "flux": "24.833", "flux_err": "0.457"}, {"hjd": "2457032.88214", "camera": "ba", "mag": "12.928", "mag_err": "0.02", "flux": "25.632", "flux_err": "0.472"}, {"hjd": "2457310.07428", "camera": "ba", "mag": "13.01", "mag_err": "0.02344", "flux": "23.752", "flux_err": "0.512"}, {"hjd": "2457283.7973", "camera": "bg", "mag": "12.979", "mag_err": "0.02", "flux": "24.682", "flux_err": "0.454"}, {"hjd": "2457346.62309", "camera": "bg", "mag": "12.895", "mag_err": "0.02", "flux": "26.661", "flux_err": "0.491"}, {"hjd": "2458078.03039", "camera": "ba", "mag": "12.938", "mag_err": "0.02", "flux": "25.378", "flux_err": "0.467"}, {"hjd": "2458117.81797", "camera": "bg", "mag": "12.975", "mag_err": "0.02", "flux": "24.765", "flux_err": "0.456"}, {"hjd": "2457760.7094", "camera": "bg", "mag": "12.911", "mag_err": "0.02", "flux": "26.282", "flux_err": "0.484"}, {"hjd": "2458133.82728", "camera": "ba", "mag": "12.986", "mag_err": "0.02", "flux": "24.282", "flux_err": "0.447"}, {"hjd": "2457799.59704", "camera": "bg", "mag": "12.945", "mag_err": "0.02", "flux": "25.463", "flux_err": "0.469"}, {"hjd": "2457421.7424", "camera": "bg", "mag": "12.92", "mag_err": "0.02", "flux": "26.061", "flux_err": "0.48"}, {"hjd": "2457402.77996", "camera": "bg", "mag": "12.954", "mag_err": "0.02", "flux": "25.259", "flux_err": "0.465"}, {"hjd": "2458145.79409", "camera": "ba", "mag": "12.984", "mag_err": "0.02", "flux": "24.312", "flux_err": "0.447"}, {"hjd": "2458193.61296", "camera": "bg", "mag": "12.961", "mag_err": "0.02", "flux": "25.081", "flux_err": "0.461"}, {"hjd": "2458413.08269", "camera": "ba", "mag": "12.914", "mag_err": "0.02", "flux": "25.965", "flux_err": "0.478"}, {"hjd": "2457360.61722", "camera": "bg", "mag": "12.973", "mag_err": "0.02", "flux": "24.825", "flux_err": "0.457"}, {"hjd": "2458197.59838", "camera": "bg", "mag": "12.966", "mag_err": "0.02", "flux": "24.978", "flux_err": "0.46"}, {"hjd": "2457010.71357", "camera": "be", "mag": "12.992", "mag_err": "0.02347", "flux": "23.838", "flux_err": "0.515"}, {"hjd": "2457698.74571", "camera": "bg", "mag": "12.975", "mag_err": "0.02", "flux": "24.76", "flux_err": "0.456"}, {"hjd": "2457879.47175", "camera": "bg", "mag": "13.073", "mag_err": "0.02307", "flux": "22.638", "flux_err": "0.48"}, {"hjd": "2457757.85149", "camera": "ba", "mag": "12.976", "mag_err": "0.02", "flux": "24.529", "flux_err": "0.451"}, {"hjd": "2457980.88882", "camera": "bg", "mag": "12.924", "mag_err": "0.02", "flux": "25.972", "flux_err": "0.478"}, {"hjd": "2457013.91889", "camera": "ba", "mag": "12.962", "mag_err": "0.02", "flux": "24.828", "flux_err": "0.457"}, {"hjd": "2458028.82776", "camera": "bg", "mag": "12.977", "mag_err": "0.02", "flux": "24.714", "flux_err": "0.455"}, {"hjd": "2457699.01331", "camera": "ba", "mag": "12.99", "mag_err": "0.0236", "flux": "24.179", "flux_err": "0.525"}, {"hjd": "2456984.97327", "camera": "ba", "mag": "12.942", "mag_err": "0.02", "flux": "25.286", "flux_err": "0.465"}, {"hjd": "2456979.97878", "camera": "ba", "mag": "12.971", "mag_err": "0.02", "flux": "24.614", "flux_err": "0.453"}, {"hjd": "2457644.81016", "camera": "bg", "mag": "12.978", "mag_err": "0.02", "flux": "24.695", "flux_err": "0.454"}, {"hjd": "2457816.65861", "camera": "bg", "mag": "12.951", "mag_err": "0.02", "flux": "25.318", "flux_err": "0.466"}, {"hjd": "2457651.80957", "camera": "bg", "mag": "12.981", "mag_err": "0.02", "flux": "24.624", "flux_err": "0.453"}, {"hjd": "2458132.83009", "camera": "ba", "mag": "12.968", "mag_err": "0.02", "flux": "24.669", "flux_err": "0.454"}, {"hjd": "2457719.81828", "camera": "bg", "mag": "12.874", "mag_err": "0.02", "flux": "27.173", "flux_err": "0.5"}, {"hjd": "2458092.66289", "camera": "bg", "mag": "12.951", "mag_err": "0.02", "flux": "25.324", "flux_err": "0.466"}, {"hjd": "2457100.60969", "camera": "be", "mag": "12.957", "mag_err": "0.02", "flux": "24.614", "flux_err": "0.453"}, {"hjd": "2458143.57365", "camera": "bg", "mag": "12.934", "mag_err": "0.02", "flux": "25.725", "flux_err": "0.473"}, {"hjd": "2457828.62413", "camera": "bg", "mag": "12.907", "mag_err": "0.02", "flux": "26.359", "flux_err": "0.485"}, {"hjd": "2458007.81412", "camera": "bg", "mag": "12.92", "mag_err": "0.02", "flux": "26.062", "flux_err": "0.48"}, {"hjd": "2456638.84784", "camera": "ba", "mag": "12.9", "mag_err": "0.02", "flux": "26.262", "flux_err": "0.483"}, {"hjd": "2456882.8984", "camera": "be", "mag": "12.97", "mag_err": "0.02", "flux": "24.309", "flux_err": "0.447"}, {"hjd": "2457612.8909", "camera": "bg", "mag": "12.983", "mag_err": "0.02", "flux": "24.583", "flux_err": "0.452"}, {"hjd": "2456988.70339", "camera": "be", "mag": "12.963", "mag_err": "0.02", "flux": "24.485", "flux_err": "0.451"}, {"hjd": "2458131.87959", "camera": "ba", "mag": "12.946", "mag_err": "0.02", "flux": "25.215", "flux_err": "0.464"}, {"hjd": "2458135.58754", "camera": "bg", "mag": "12.949", "mag_err": "0.02", "flux": "25.368", "flux_err": "0.467"}, {"hjd": "2458123.89854", "camera": "ba", "mag": "12.938", "mag_err": "0.02", "flux": "25.382", "flux_err": "0.467"}, {"hjd": "2457408.81586", "camera": "ba", "mag": "12.891", "mag_err": "0.02", "flux": "26.499", "flux_err": "0.488"}, {"hjd": "2457874.48175", "camera": "bg", "mag": "12.953", "mag_err": "0.02", "flux": "25.275", "flux_err": "0.465"}, {"hjd": "2456937.78043", "camera": "be", "mag": "12.94", "mag_err": "0.02", "flux": "25.006", "flux_err": "0.46"}, {"hjd": "2456912.90441", "camera": "be", "mag": "12.962", "mag_err": "0.02", "flux": "24.489", "flux_err": "0.451"}, {"hjd": "2457403.5458", "camera": "bg", "mag": "12.97", "mag_err": "0.02", "flux": "24.885", "flux_err": "0.458"}, {"hjd": "2457327.82159", "camera": "bg", "mag": "12.911", "mag_err": "0.02", "flux": "26.269", "flux_err": "0.483"}, {"hjd": "2457008.94694", "camera": "ba", "mag": "12.92", "mag_err": "0.02", "flux": "25.823", "flux_err": "0.475"}, {"hjd": "2456971.97888", "camera": "ba", "mag": "12.96", "mag_err": "0.02", "flux": "24.86", "flux_err": "0.457"}, {"hjd": "2457395.70159", "camera": "bg", "mag": "12.996", "mag_err": "0.02", "flux": "24.291", "flux_err": "0.447"}, {"hjd": "2457050.63539", "camera": "be", "mag": "12.951", "mag_err": "0.02", "flux": "24.737", "flux_err": "0.455"}, {"hjd": "2457418.74783", "camera": "bg", "mag": "12.997", "mag_err": "0.02", "flux": "24.278", "flux_err": "0.447"}, {"hjd": "2458165.66398", "camera": "bg", "mag": "12.992", "mag_err": "0.02", "flux": "24.376", "flux_err": "0.449"}, {"hjd": "2458141.54727", "camera": "bg", "mag": "12.956", "mag_err": "0.02", "flux": "25.216", "flux_err": "0.464"}, {"hjd": "2457466.60965", "camera": "bg", "mag": "12.983", "mag_err": "0.02", "flux": "24.597", "flux_err": "0.453"}, {"hjd": "2458086.70069", "camera": "bg", "mag": "12.938", "mag_err": "0.02", "flux": "25.618", "flux_err": "0.471"}, {"hjd": "2458108.79601", "camera": "bg", "mag": "12.946", "mag_err": "0.02", "flux": "25.444", "flux_err": "0.468"}, {"hjd": "2457113.53169", "camera": "be", "mag": "12.92", "mag_err": "0.02", "flux": "25.466", "flux_err": "0.469"}, {"hjd": "2457362.67895", "camera": "bg", "mag": "12.913", "mag_err": "0.02", "flux": "26.236", "flux_err": "0.483"}, {"hjd": "2457388.78855", "camera": "bg", "mag": "12.965", "mag_err": "0.02", "flux": "24.989", "flux_err": "0.46"}, {"hjd": "2457318.06109", "camera": "ba", "mag": "13.002", "mag_err": "0.0235", "flux": "23.917", "flux_err": "0.517"}, {"hjd": "2457743.66218", "camera": "bg", "mag": "12.893", "mag_err": "0.02", "flux": "26.705", "flux_err": "0.491"}, {"hjd": "2457036.88159", "camera": "ba", "mag": "12.916", "mag_err": "0.02", "flux": "25.923", "flux_err": "0.477"}, {"hjd": "2457445.58708", "camera": "bg", "mag": "12.977", "mag_err": "0.02", "flux": "24.727", "flux_err": "0.455"}, {"hjd": "2457348.83222", "camera": "bg", "mag": "12.995", "mag_err": "0.02", "flux": "24.313", "flux_err": "0.447"}, {"hjd": "2457460.61213", "camera": "bg", "mag": "12.94", "mag_err": "0.02", "flux": "25.588", "flux_err": "0.471"}, {"hjd": "2458124.68579", "camera": "bg", "mag": "12.961", "mag_err": "0.02", "flux": "25.094", "flux_err": "0.462"}, {"hjd": "2456919.10279", "camera": "ba", "mag": "12.934", "mag_err": "0.02", "flux": "25.491", "flux_err": "0.469"}, {"hjd": "2457638.82207", "camera": "bg", "mag": "12.928", "mag_err": "0.02", "flux": "25.876", "flux_err": "0.476"}, {"hjd": "2458419.04666", "camera": "ba", "mag": "12.968", "mag_err": "0.02", "flux": "24.691", "flux_err": "0.454"}, {"hjd": "2457789.73327", "camera": "bg", "mag": "12.94", "mag_err": "0.02", "flux": "25.591", "flux_err": "0.471"}, {"hjd": "2457013.69587", "camera": "be", "mag": "12.939", "mag_err": "0.02", "flux": "25.014", "flux_err": "0.46"}, {"hjd": "2457033.75821", "camera": "be", "mag": "12.643", "mag_err": "0.02", "flux": "32.873", "flux_err": "0.605"}, {"hjd": "2457798.66559", "camera": "bg", "mag": "12.93", "mag_err": "0.02", "flux": "25.826", "flux_err": "0.475"}, {"hjd": "2456965.7467", "camera": "be", "mag": "12.948", "mag_err": "0.02", "flux": "24.81", "flux_err": "0.456"}, {"hjd": "2458097.63485", "camera": "bg", "mag": "12.934", "mag_err": "0.02", "flux": "25.714", "flux_err": "0.473"}, {"hjd": "2457955.93689", "camera": "bg", "mag": "12.947", "mag_err": "0.02", "flux": "25.423", "flux_err": "0.468"}, {"hjd": "2457617.8787", "camera": "bg", "mag": "12.926", "mag_err": "0.02", "flux": "25.904", "flux_err": "0.477"}, {"hjd": "2457394.90282", "camera": "ba", "mag": "12.97", "mag_err": "0.02", "flux": "24.639", "flux_err": "0.453"}, {"hjd": "2457592.93048", "camera": "bg", "mag": "12.977", "mag_err": "0.02", "flux": "24.732", "flux_err": "0.455"}, {"hjd": "2457377.71255", "camera": "bg", "mag": "12.913", "mag_err": "0.02", "flux": "26.213", "flux_err": "0.482"}, {"hjd": "2457446.67038", "camera": "bg", "mag": "12.957", "mag_err": "0.02", "flux": "25.182", "flux_err": "0.463"}, {"hjd": "2457767.67715", "camera": "bg", "mag": "12.951", "mag_err": "0.02", "flux": "25.312", "flux_err": "0.466"}, {"hjd": "2457114.56486", "camera": "be", "mag": "12.905", "mag_err": "0.02", "flux": "25.829", "flux_err": "0.475"}, {"hjd": "2457227.92796", "camera": "be", "mag": "12.973", "mag_err": "0.02", "flux": "24.256", "flux_err": "0.446"}, {"hjd": "2458043.80384", "camera": "bg", "mag": "12.999", "mag_err": "0.02", "flux": "24.239", "flux_err": "0.446"}, {"hjd": "2458029.75507", "camera": "bg", "mag": "12.969", "mag_err": "0.02", "flux": "24.916", "flux_err": "0.458"}, {"hjd": "2456918.84213", "camera": "be", "mag": "12.935", "mag_err": "0.02", "flux": "25.123", "flux_err": "0.462"}, {"hjd": "2456621.87928", "camera": "ba", "mag": "12.902", "mag_err": "0.02", "flux": "26.239", "flux_err": "0.483"}, {"hjd": "2458090.78665", "camera": "bg", "mag": "12.96", "mag_err": "0.02", "flux": "25.121", "flux_err": "0.462"}, {"hjd": "2457005.71197", "camera": "be", "mag": "12.952", "mag_err": "0.02", "flux": "24.729", "flux_err": "0.455"}, {"hjd": "2456884.89331", "camera": "be", "mag": "12.942", "mag_err": "0.02", "flux": "24.962", "flux_err": "0.459"}, {"hjd": "2456943.06033", "camera": "ba", "mag": "12.952", "mag_err": "0.02", "flux": "25.07", "flux_err": "0.461"}, {"hjd": "2457481.53912", "camera": "bg", "mag": "12.99", "mag_err": "0.02", "flux": "24.44", "flux_err": "0.45"}, {"hjd": "2457773.75501", "camera": "bg", "mag": "12.925", "mag_err": "0.02", "flux": "25.927", "flux_err": "0.477"}, {"hjd": "2456675.86421", "camera": "ba", "mag": "12.95", "mag_err": "0.02", "flux": "25.119", "flux_err": "0.462"}, {"hjd": "2458128.6892", "camera": "bg", "mag": "12.941", "mag_err": "0.02", "flux": "25.567", "flux_err": "0.47"}, {"hjd": "2457958.9304", "camera": "bg", "mag": "12.957", "mag_err": "0.02", "flux": "25.174", "flux_err": "0.463"}, {"hjd": "2458016.87319", "camera": "bg", "mag": "12.966", "mag_err": "0.02", "flux": "24.967", "flux_err": "0.459"}, {"hjd": "2458153.62285", "camera": "bg", "mag": "12.979", "mag_err": "0.02", "flux": "24.684", "flux_err": "0.454"}, {"hjd": "2457655.79186", "camera": "bg", "mag": "12.934", "mag_err": "0.02", "flux": "25.727", "flux_err": "0.473"}, {"hjd": "2458103.70017", "camera": "bg", "mag": "12.956", "mag_err": "0.02", "flux": "25.199", "flux_err": "0.464"}, {"hjd": "2457334.80826", "camera": "bg", "mag": "12.921", "mag_err": "0.02", "flux": "26.023", "flux_err": "0.479"}, {"hjd": "2457857.50573", "camera": "bg", "mag": "12.915", "mag_err": "0.02", "flux": "26.188", "flux_err": "0.482"}, {"hjd": "2457069.59854", "camera": "be", "mag": "12.982", "mag_err": "0.02355", "flux": "24.052", "flux_err": "0.521"}, {"hjd": "2457063.67388", "camera": "be", "mag": "12.932", "mag_err": "0.02", "flux": "25.193", "flux_err": "0.464"}, {"hjd": "2457007.84259", "camera": "be", "mag": "12.951", "mag_err": "0.02", "flux": "24.748", "flux_err": "0.455"}, {"hjd": "2457623.86545", "camera": "bg", "mag": "12.932", "mag_err": "0.02", "flux": "25.76", "flux_err": "0.474"}, {"hjd": "2456975.72115", "camera": "be", "mag": "12.969", "mag_err": "0.02", "flux": "24.342", "flux_err": "0.448"}, {"hjd": "2458125.89555", "camera": "ba", "mag": "12.97", "mag_err": "0.02", "flux": "24.626", "flux_err": "0.453"}, {"hjd": "2457784.72042", "camera": "bg", "mag": "12.973", "mag_err": "0.02", "flux": "24.821", "flux_err": "0.457"}, {"hjd": "2456862.94142", "camera": "be", "mag": "12.991", "mag_err": "0.02348", "flux": "23.859", "flux_err": "0.515"}, {"hjd": "2458148.78981", "camera": "ba", "mag": "12.987", "mag_err": "0.02", "flux": "24.259", "flux_err": "0.446"}, {"hjd": "2457607.90466", "camera": "bg", "mag": "12.891", "mag_err": "0.02", "flux": "26.759", "flux_err": "0.492"}, {"hjd": "2457456.53831", "camera": "bg", "mag": "12.91", "mag_err": "0.02", "flux": "26.3", "flux_err": "0.484"}, {"hjd": "2456873.92922", "camera": "be", "mag": "12.959", "mag_err": "0.02", "flux": "24.572", "flux_err": "0.452"}, {"hjd": "2457854.51958", "camera": "bg", "mag": "13.013", "mag_err": "0.0235", "flux": "23.911", "flux_err": "0.517"}, {"hjd": "2457355.70036", "camera": "bg", "mag": "12.926", "mag_err": "0.02", "flux": "25.911", "flux_err": "0.477"}, {"hjd": "2457654.78348", "camera": "bg", "mag": "12.939", "mag_err": "0.02", "flux": "25.597", "flux_err": "0.471"}, {"hjd": "2457090.57839", "camera": "be", "mag": "12.883", "mag_err": "0.02", "flux": "26.351", "flux_err": "0.485"}, {"hjd": "2457420.743", "camera": "bg", "mag": "12.904", "mag_err": "0.02", "flux": "26.436", "flux_err": "0.486"}, {"hjd": "2458031.11457", "camera": "ba", "mag": "12.958", "mag_err": "0.02", "flux": "24.931", "flux_err": "0.459"}, {"hjd": "2457722.61371", "camera": "bg", "mag": "12.985", "mag_err": "0.02", "flux": "24.543", "flux_err": "0.452"}, {"hjd": "2457322.82576", "camera": "bg", "mag": "12.954", "mag_err": "0.02", "flux": "25.256", "flux_err": "0.465"}, {"hjd": "2457629.84574", "camera": "bg", "mag": "12.927", "mag_err": "0.02", "flux": "25.899", "flux_err": "0.477"}, {"hjd": "2457645.85651", "camera": "bg", "mag": "12.926", "mag_err": "0.02", "flux": "25.915", "flux_err": "0.477"}, {"hjd": "2456598.00048", "camera": "ba", "mag": "12.942", "mag_err": "0.02", "flux": "25.27", "flux_err": "0.465"}, {"hjd": "2456931.80335", "camera": "be", "mag": "12.931", "mag_err": "0.02", "flux": "25.201", "flux_err": "0.464"}, {"hjd": "2457689.83454", "camera": "bg", "mag": "12.913", "mag_err": "0.02", "flux": "26.218", "flux_err": "0.482"}, {"hjd": "2457659.86688", "camera": "bg", "mag": "12.975", "mag_err": "0.02", "flux": "24.762", "flux_err": "0.456"}, {"hjd": "2458144.64679", "camera": "bg", "mag": "12.939", "mag_err": "0.02", "flux": "25.6", "flux_err": "0.471"}, {"hjd": "2457364.73772", "camera": "bg", "mag": "12.992", "mag_err": "0.02", "flux": "24.374", "flux_err": "0.448"}, {"hjd": "2458056.79362", "camera": "bg", "mag": "12.987", "mag_err": "0.02", "flux": "24.502", "flux_err": "0.451"}, {"hjd": "2458151.68909", "camera": "bg", "mag": "12.923", "mag_err": "0.02", "flux": "25.976", "flux_err": "0.478"}, {"hjd": "2457667.74607", "camera": "bg", "mag": "12.965", "mag_err": "0.02", "flux": "24.994", "flux_err": "0.46"}, {"hjd": "2457249.87964", "camera": "be", "mag": "12.922", "mag_err": "0.02", "flux": "25.412", "flux_err": "0.468"}, {"hjd": "2458035.85248", "camera": "bg", "mag": "12.946", "mag_err": "0.02", "flux": "25.433", "flux_err": "0.468"}, {"hjd": "2456793.45499", "camera": "be", "mag": "12.962", "mag_err": "0.02", "flux": "24.5", "flux_err": "0.451"}, {"hjd": "2458139.5748", "camera": "bg", "mag": "12.944", "mag_err": "0.02", "flux": "25.481", "flux_err": "0.469"}, {"hjd": "2457826.51054", "camera": "bg", "mag": "12.964", "mag_err": "0.02", "flux": "25.024", "flux_err": "0.46"}, {"hjd": "2457305.83335", "camera": "bg", "mag": "12.979", "mag_err": "0.02", "flux": "24.679", "flux_err": "0.454"}, {"hjd": "2457387.75434", "camera": "bg", "mag": "13.0", "mag_err": "0.02361", "flux": "24.2", "flux_err": "0.526"}, {"hjd": "2457003.94035", "camera": "ba", "mag": "12.942", "mag_err": "0.02", "flux": "25.281", "flux_err": "0.465"}, {"hjd": "2458101.9584", "camera": "ba", "mag": "12.95", "mag_err": "0.02", "flux": "25.096", "flux_err": "0.462"}, {"hjd": "2457042.64466", "camera": "be", "mag": "12.989", "mag_err": "0.0235", "flux": "23.887", "flux_err": "0.516"}, {"hjd": "2457870.4843", "camera": "bg", "mag": "12.956", "mag_err": "0.02", "flux": "25.195", "flux_err": "0.464"}, {"hjd": "2457834.59842", "camera": "bg", "mag": "12.955", "mag_err": "0.02", "flux": "25.24", "flux_err": "0.464"}, {"hjd": "2457844.57743", "camera": "bg", "mag": "12.917", "mag_err": "0.02", "flux": "26.121", "flux_err": "0.481"}, {"hjd": "2456936.7987", "camera": "be", "mag": "12.97", "mag_err": "0.02", "flux": "24.319", "flux_err": "0.447"}, {"hjd": "2457470.60033", "camera": "bg", "mag": "12.924", "mag_err": "0.02", "flux": "25.971", "flux_err": "0.478"}, {"hjd": "2458189.60485", "camera": "bg", "mag": "12.941", "mag_err": "0.02", "flux": "25.553", "flux_err": "0.47"}, {"hjd": "2456906.91408", "camera": "be", "mag": "12.91", "mag_err": "0.02", "flux": "25.706", "flux_err": "0.473"}, {"hjd": "2456923.82346", "camera": "be", "mag": "12.949", "mag_err": "0.02", "flux": "24.785", "flux_err": "0.456"}, {"hjd": "2458010.84931", "camera": "bg", "mag": "12.948", "mag_err": "0.02", "flux": "25.384", "flux_err": "0.467"}, {"hjd": "2457094.60682", "camera": "be", "mag": "12.898", "mag_err": "0.02", "flux": "25.974", "flux_err": "0.478"}, {"hjd": "2457424.81333", "camera": "ba", "mag": "12.916", "mag_err": "0.02", "flux": "25.913", "flux_err": "0.477"}, {"hjd": "2457763.85421", "camera": "ba", "mag": "12.962", "mag_err": "0.02", "flux": "24.826", "flux_err": "0.457"}, {"hjd": "2458140.83914", "camera": "ba", "mag": "12.984", "mag_err": "0.02", "flux": "24.311", "flux_err": "0.447"}, {"hjd": "2456978.01521", "camera": "ba", "mag": "12.928", "mag_err": "0.02", "flux": "25.599", "flux_err": "0.471"}, {"hjd": "2457390.75079", "camera": "bg", "mag": "12.964", "mag_err": "0.02", "flux": "25.025", "flux_err": "0.46"}, {"hjd": "2458080.68891", "camera": "bg", "mag": "12.946", "mag_err": "0.02", "flux": "25.448", "flux_err": "0.468"}, {"hjd": "2457764.73533", "camera": "bg", "mag": "12.964", "mag_err": "0.02", "flux": "25.024", "flux_err": "0.46"}, {"hjd": "2457331.77817", "camera": "bg", "mag": "12.914", "mag_err": "0.02", "flux": "26.191", "flux_err": "0.482"}, {"hjd": "2457687.69266", "camera": "bg", "mag": "12.957", "mag_err": "0.02", "flux": "25.187", "flux_err": "0.463"}, {"hjd": "2457022.66676", "camera": "be", "mag": "12.997", "mag_err": "0.02343", "flux": "23.713", "flux_err": "0.511"}, {"hjd": "2458407.0775", "camera": "ba", "mag": "12.97", "mag_err": "0.02", "flux": "24.664", "flux_err": "0.454"}, {"hjd": "2457278.88525", "camera": "bg", "mag": "12.969", "mag_err": "0.02", "flux": "24.906", "flux_err": "0.458"}, {"hjd": "2457357.78895", "camera": "bg", "mag": "12.928", "mag_err": "0.02", "flux": "25.875", "flux_err": "0.476"}, {"hjd": "2456885.89384", "camera": "be", "mag": "12.951", "mag_err": "0.02", "flux": "24.743", "flux_err": "0.455"}, {"hjd": "2458142.58192", "camera": "bg", "mag": "12.954", "mag_err": "0.02", "flux": "25.248", "flux_err": "0.465"}, {"hjd": "2457771.74946", "camera": "bg", "mag": "12.953", "mag_err": "0.02", "flux": "25.267", "flux_err": "0.465"}, {"hjd": "2458084.66165", "camera": "bg", "mag": "12.919", "mag_err": "0.02", "flux": "26.077", "flux_err": "0.48"}, {"hjd": "2456894.89746", "camera": "be", "mag": "12.949", "mag_err": "0.02", "flux": "24.794", "flux_err": "0.456"}, {"hjd": "2457757.7313", "camera": "bg", "mag": "12.954", "mag_err": "0.02", "flux": "25.258", "flux_err": "0.465"}, {"hjd": "2456925.86645", "camera": "be", "mag": "12.96", "mag_err": "0.02", "flux": "24.539", "flux_err": "0.452"}, {"hjd": "2456881.90252", "camera": "be", "mag": "12.95", "mag_err": "0.02", "flux": "24.762", "flux_err": "0.456"}, {"hjd": "2457001.70559", "camera": "be", "mag": "12.93", "mag_err": "0.02", "flux": "25.219", "flux_err": "0.464"}, {"hjd": "2456930.86546", "camera": "be", "mag": "12.938", "mag_err": "0.02", "flux": "25.036", "flux_err": "0.461"}, {"hjd": "2457707.69493", "camera": "bg", "mag": "12.927", "mag_err": "0.02", "flux": "25.888", "flux_err": "0.476"}, {"hjd": "2457750.60539", "camera": "bg", "mag": "12.914", "mag_err": "0.02", "flux": "26.191", "flux_err": "0.482"}, {"hjd": "2456982.97407", "camera": "ba", "mag": "12.954", "mag_err": "0.02", "flux": "25.002", "flux_err": "0.46"}, {"hjd": "2457837.59539", "camera": "bg", "mag": "12.939", "mag_err": "0.02", "flux": "25.599", "flux_err": "0.471"}, {"hjd": "2458101.61014", "camera": "bg", "mag": "12.948", "mag_err": "0.02", "flux": "25.387", "flux_err": "0.467"}, {"hjd": "2457032.65451", "camera": "be", "mag": "12.953", "mag_err": "0.02", "flux": "24.692", "flux_err": "0.454"}, {"hjd": "2457137.49393", "camera": "be", "mag": "12.89", "mag_err": "0.02", "flux": "26.172", "flux_err": "0.482"}, {"hjd": "2457671.7362", "camera": "bg", "mag": "12.978", "mag_err": "0.02", "flux": "24.708", "flux_err": "0.455"}, {"hjd": "2458178.64189", "camera": "bg", "mag": "12.932", "mag_err": "0.02", "flux": "25.76", "flux_err": "0.474"}, {"hjd": "2458019.78362", "camera": "bg", "mag": "12.92", "mag_err": "0.02", "flux": "26.055", "flux_err": "0.479"}, {"hjd": "2458141.79892", "camera": "ba", "mag": "12.972", "mag_err": "0.02", "flux": "24.595", "flux_err": "0.453"}, {"hjd": "2457315.06223", "camera": "ba", "mag": "12.944", "mag_err": "0.02", "flux": "25.255", "flux_err": "0.465"}, {"hjd": "2457427.63238", "camera": "bg", "mag": "12.966", "mag_err": "0.02", "flux": "24.965", "flux_err": "0.459"}, {"hjd": "2456981.97771", "camera": "ba", "mag": "12.934", "mag_err": "0.02", "flux": "25.478", "flux_err": "0.469"}, {"hjd": "2457880.46393", "camera": "bg", "mag": "12.964", "mag_err": "0.02", "flux": "25.016", "flux_err": "0.46"}, {"hjd": "2457373.53839", "camera": "bg", "mag": "12.865", "mag_err": "0.02", "flux": "27.406", "flux_err": "0.504"}, {"hjd": "2457379.85003", "camera": "bg", "mag": "13.011", "mag_err": "0.02352", "flux": "23.963", "flux_err": "0.518"}, {"hjd": "2458449.00846", "camera": "ba", "mag": "12.978", "mag_err": "0.02", "flux": "24.482", "flux_err": "0.45"}, {"hjd": "2456938.79488", "camera": "be", "mag": "12.95", "mag_err": "0.02", "flux": "24.772", "flux_err": "0.456"}, {"hjd": "2456905.1314", "camera": "ba", "mag": "12.9", "mag_err": "0.02", "flux": "26.3", "flux_err": "0.484"}, {"hjd": "2457049.79829", "camera": "ba", "mag": "12.971", "mag_err": "0.02", "flux": "24.609", "flux_err": "0.453"}, {"hjd": "2457863.51231", "camera": "bg", "mag": "12.956", "mag_err": "0.02", "flux": "25.217", "flux_err": "0.464"}, {"hjd": "2458076.63985", "camera": "bg", "mag": "12.937", "mag_err": "0.02", "flux": "25.658", "flux_err": "0.472"}, {"hjd": "2457045.63845", "camera": "be", "mag": "12.99", "mag_err": "0.02349", "flux": "23.863", "flux_err": "0.516"}, {"hjd": "2457779.61653", "camera": "bg", "mag": "12.963", "mag_err": "0.02", "flux": "25.038", "flux_err": "0.461"}, {"hjd": "2457029.65613", "camera": "be", "mag": "12.98", "mag_err": "0.02357", "flux": "24.097", "flux_err": "0.522"}]